ImageManager.py
__init__.py
ImageManager_EagleProjects-0.0.1.dist-info/METADATA
ImageManager_EagleProjects-0.0.1.dist-info/WHEEL
ImageManager_EagleProjects-0.0.1.dist-info/top_level.txt
ImageManager_EagleProjects-0.0.1.dist-info/RECORD
