Metadata-Version: 2.1
Name: ImageManager_EagleProjects
Version: 0.0.1
Summary: package handling click on image and waiting with pyautogui
Author-email: Example Giovanni Gargiulo <ggargiulo@eagleprojects.it>
Project-URL: Homepage, https://github.com/pypa/sampleproject
Project-URL: Bug Tracker, https://github.com/pypa/sampleproject/issues
Classifier: Programming Language :: Python :: 3
Classifier: License :: OSI Approved :: MIT License
Classifier: Operating System :: OS Independent
Requires-Python: >=3.7
